IpythonJiaohushiJisuanHeShujuKeshihua/README.md
IpythonJiaohushiJisuanHeShujuKeshihua/__init__.py
IpythonJiaohushiJisuanHeShujuKeshihua/__main__.py
IpythonJiaohushiJisuanHeShujuKeshihua/file.epub
IpythonJiaohushiJisuanHeShujuKeshihua/index.html
IpythonJiaohushiJisuanHeShujuKeshihua/css/__init__.py
IpythonJiaohushiJisuanHeShujuKeshihua/css/annotations.css
IpythonJiaohushiJisuanHeShujuKeshihua/css/main.css
IpythonJiaohushiJisuanHeShujuKeshihua/css/normalize.css
IpythonJiaohushiJisuanHeShujuKeshihua/css/popup.css
IpythonJiaohushiJisuanHeShujuKeshihua/font/__init__.py
IpythonJiaohushiJisuanHeShujuKeshihua/font/fontello.eot
IpythonJiaohushiJisuanHeShujuKeshihua/font/fontello.svg
IpythonJiaohushiJisuanHeShujuKeshihua/font/fontello.ttf
IpythonJiaohushiJisuanHeShujuKeshihua/font/fontello.woff
IpythonJiaohushiJisuanHeShujuKeshihua/img/__init__.py
IpythonJiaohushiJisuanHeShujuKeshihua/img/annotator-glyph-sprite.png
IpythonJiaohushiJisuanHeShujuKeshihua/img/annotator-icon-sprite.png
IpythonJiaohushiJisuanHeShujuKeshihua/img/apple-touch-icon.png
IpythonJiaohushiJisuanHeShujuKeshihua/img/cancelfullscreen.png
IpythonJiaohushiJisuanHeShujuKeshihua/img/close.png
IpythonJiaohushiJisuanHeShujuKeshihua/img/fullscreen.png
IpythonJiaohushiJisuanHeShujuKeshihua/img/loader.gif
IpythonJiaohushiJisuanHeShujuKeshihua/img/menu-icon.png
IpythonJiaohushiJisuanHeShujuKeshihua/img/save.png
IpythonJiaohushiJisuanHeShujuKeshihua/img/saved.png
IpythonJiaohushiJisuanHeShujuKeshihua/img/settings-s.png
IpythonJiaohushiJisuanHeShujuKeshihua/img/settings.png
IpythonJiaohushiJisuanHeShujuKeshihua/img/star.png
IpythonJiaohushiJisuanHeShujuKeshihua/js/__init__.py
IpythonJiaohushiJisuanHeShujuKeshihua/js/epub.js
IpythonJiaohushiJisuanHeShujuKeshihua/js/epub.min.js
IpythonJiaohushiJisuanHeShujuKeshihua/js/epub.min.map
IpythonJiaohushiJisuanHeShujuKeshihua/js/hooks.min.js
IpythonJiaohushiJisuanHeShujuKeshihua/js/hooks.min.map
IpythonJiaohushiJisuanHeShujuKeshihua/js/reader.js
ipython_jiaohushi_jisuan_he_shuju_keshihua-2024.3.1.0.dist-info/METADATA
ipython_jiaohushi_jisuan_he_shuju_keshihua-2024.3.1.0.dist-info/WHEEL
ipython_jiaohushi_jisuan_he_shuju_keshihua-2024.3.1.0.dist-info/entry_points.txt
ipython_jiaohushi_jisuan_he_shuju_keshihua-2024.3.1.0.dist-info/top_level.txt
ipython_jiaohushi_jisuan_he_shuju_keshihua-2024.3.1.0.dist-info/RECORD
